com/__init__.py
com/johnsnowlabs/__init__.py
com/johnsnowlabs/ml/__init__.py
com/johnsnowlabs/ml/ai/__init__.py
com/johnsnowlabs/nlp/__init__.py
sparknlp/__init__.py
sparknlp/annotation.py
sparknlp/annotation_audio.py
sparknlp/annotation_image.py
sparknlp/functions.py
sparknlp/upload_to_hub.py
sparknlp/util.py
sparknlp/annotator/__init__.py
sparknlp/annotator/chunk2_doc.py
sparknlp/annotator/chunker.py
sparknlp/annotator/dataframe_optimizer.py
sparknlp/annotator/date2_chunk.py
sparknlp/annotator/document_character_text_splitter.py
sparknlp/annotator/document_normalizer.py
sparknlp/annotator/document_token_splitter.py
sparknlp/annotator/document_token_splitter_test.py
sparknlp/annotator/graph_extraction.py
sparknlp/annotator/lemmatizer.py
sparknlp/annotator/n_gram_generator.py
sparknlp/annotator/normalizer.py
sparknlp/annotator/stemmer.py
sparknlp/annotator/stop_words_cleaner.py
sparknlp/annotator/tf_ner_dl_graph_builder.py
sparknlp/annotator/token2_chunk.py
sparknlp/annotator/audio/__init__.py
sparknlp/annotator/audio/hubert_for_ctc.py
sparknlp/annotator/audio/wav2vec2_for_ctc.py
sparknlp/annotator/audio/whisper_for_ctc.py
sparknlp/annotator/classifier_dl/__init__.py
sparknlp/annotator/classifier_dl/albert_for_multiple_choice.py
sparknlp/annotator/classifier_dl/albert_for_question_answering.py
sparknlp/annotator/classifier_dl/albert_for_sequence_classification.py
sparknlp/annotator/classifier_dl/albert_for_token_classification.py
sparknlp/annotator/classifier_dl/albert_for_zero_shot_classification.py
sparknlp/annotator/classifier_dl/bart_for_zero_shot_classification.py
sparknlp/annotator/classifier_dl/bert_for_multiple_choice.py
sparknlp/annotator/classifier_dl/bert_for_question_answering.py
sparknlp/annotator/classifier_dl/bert_for_sequence_classification.py
sparknlp/annotator/classifier_dl/bert_for_token_classification.py
sparknlp/annotator/classifier_dl/bert_for_zero_shot_classification.py
sparknlp/annotator/classifier_dl/camembert_for_question_answering.py
spark_nlp-6.3.2.dist-info/METADATA
spark_nlp-6.3.2.dist-info/WHEEL
spark_nlp-6.3.2.dist-info/top_level.txt
spark_nlp-6.3.2.dist-info/RECORD
